beatlock/__init__.py
beatlock/schedulers.py
beatlock-0.0.3.dist-info/LICENSE
beatlock-0.0.3.dist-info/METADATA
beatlock-0.0.3.dist-info/WHEEL
beatlock-0.0.3.dist-info/top_level.txt
beatlock-0.0.3.dist-info/RECORD
