Metadata-Version: 2.1
Name: beatlock
Version: 0.0.3
Summary: Celerybeat scheduler on redis-sentinel
Home-page: https://github.com/kidig/beatlock
Author: Dmitry Gerasimenko
License: MIT
Keywords: celerybeat redis sentinel scheduler
Platform: UNKNOWN
Classifier: License :: OSI Approved :: MIT License
Classifier: Programming Language :: Python
Classifier: Programming Language :: Python :: 3
Classifier: Programming Language :: Python :: 3.6
Classifier: Programming Language :: Python :: 3.7
Classifier: Programming Language :: Python :: 3.8
Classifier: Development Status :: 4 - Beta
License-File: LICENSE
Requires-Dist: celery (>=5.1.2)
Requires-Dist: django-celery-beat (>=2.0.0)
Requires-Dist: redis (>=3.5.0)
Requires-Dist: tenacity (>=6.3.1)
Requires-Dist: setuptools
